smbclient/__init__.py
smbclient/_io.py
smbclient/_os.py
smbclient/_pool.py
smbclient/path.py
smbclient/shutil.py
smbprotocol/__init__.py
smbprotocol/_text.py
smbprotocol/change_notify.py
smbprotocol/connection.py
smbprotocol/create_contexts.py
smbprotocol/dfs.py
smbprotocol/exceptions.py
smbprotocol/file_info.py
smbprotocol/header.py
smbprotocol/ioctl.py
smbprotocol/open.py
smbprotocol/query_info.py
smbprotocol/reparse_point.py
smbprotocol/security_descriptor.py
smbprotocol/session.py
smbprotocol/structure.py
smbprotocol/transport.py
smbprotocol/tree.py
smbprotocol-1.14.0.dist-info/LICENSE
smbprotocol-1.14.0.dist-info/METADATA
smbprotocol-1.14.0.dist-info/WHEEL
smbprotocol-1.14.0.dist-info/top_level.txt
smbprotocol-1.14.0.dist-info/RECORD
