Metadata-Version: 2.1
Name: smbprotocol
Version: 1.14.0
Summary: Interact with a server using the SMB 2/3 Protocol
Author-email: Jordan Borean <jborean93@gmail.com>
License: MIT License
Project-URL: homepage, https://github.com/jborean93/smbprotocol
Keywords: smb,smb2,smb3,cifs,python
Classifier: Development Status :: 4 - Beta
Classifier: License :: OSI Approved :: MIT License
Classifier: Programming Language :: Python :: 3
Classifier: Programming Language :: Python :: 3.8
Classifier: Programming Language :: Python :: 3.9
Classifier: Programming Language :: Python :: 3.10
Classifier: Programming Language :: Python :: 3.11
Classifier: Programming Language :: Python :: 3.12
Requires-Python: >=3.8
License-File: LICENSE
Requires-Dist: cryptography>=2.0
Requires-Dist: pyspnego
Provides-Extra: kerberos
Requires-Dist: pyspnego[kerberos]; extra == "kerberos"
